geargen/__init__.py
geargen/__main__.py
geargen/bevel.py
geargen/cli.py
geargen/parallel.py
geargen/profile.py
geargen-0.0.1.dist-info/licenses/LICENSE
geargen-0.0.1.dist-info/METADATA
geargen-0.0.1.dist-info/WHEEL
geargen-0.0.1.dist-info/entry_points.txt
geargen-0.0.1.dist-info/top_level.txt
geargen-0.0.1.dist-info/RECORD
