Metadata-Version: 2.4
Name: geargen
Version: 0.0.1
Summary: A command-line gear generator
Author-email: Satoshi Tanaka <overthere555@gmail.com>
License-Expression: Apache-2.0
Project-URL: Homepage, https://github.com/tana/geargen
Project-URL: Issues, https://github.com/tana/geargen/issues
Classifier: Programming Language :: Python :: 3
Classifier: Environment :: Console
Classifier: Topic :: Scientific/Engineering
Requires-Python: >=3.9
License-File: LICENSE
Requires-Dist: cadquery>=2.5.2
Dynamic: license-file
